archy/__init__.py
archy/shape.py
Archiy-1.0.0.dist-info/METADATA
Archiy-1.0.0.dist-info/WHEEL
Archiy-1.0.0.dist-info/top_level.txt
Archiy-1.0.0.dist-info/RECORD
