Metadata-Version: 2.1
Name: Archiy
Version: 1.0.0
Summary: Aerospace Mathematics
Home-page: UNKNOWN
Author: youcefi yassine
Author-email: mohamed.youcefi.etu@univ-mosta.dz
License: UNKNOWN
Keywords: python
Platform: UNKNOWN
Classifier: Development Status :: 1 - Planning
Classifier: Intended Audience :: Developers
Classifier: Programming Language :: Python :: 3
Classifier: Operating System :: Unix
Classifier: Operating System :: MacOS :: MacOS X
Classifier: Operating System :: Microsoft :: Windows
